[
  {
    "inputs": [
      {
        "internalType": "uint256",
        "name": "borrowAmountInCurrency",
        "type": "uint256"
      }
    ],
    "name": "borrow",
    "outputs": [],
    "stateMutability": "nonpayable",
    "type": "function"
  },
  {
    "inputs": [],
    "name": "deposit",
    "outputs": [],
    "stateMutability": "payable",
    "type": "function"
  },
  {
    "inputs": [
      {
        "internalType": "uint256",
        "name": "ethAmount",
        "type": "uint256"
      }
    ],
    "name": "withdraw",
    "outputs": [],
    "stateMutability": "nonpayable",
    "type": "function"
  }
]
